shm_dict/__init__.py
shm_dict/_version.py
shm_dict/shm_dict.py
tests/__init__.py
tests/test_shm_dict.py
shm_dict-2019.8.28.20.31.dist-info/LICENSE
shm_dict-2019.8.28.20.31.dist-info/LICENSE.LESSER
shm_dict-2019.8.28.20.31.dist-info/METADATA
shm_dict-2019.8.28.20.31.dist-info/WHEEL
shm_dict-2019.8.28.20.31.dist-info/top_level.txt
shm_dict-2019.8.28.20.31.dist-info/RECORD
